maintain_ner_position/__init__.py
maintain_ner_position/my_delete.py
maintain_ner_position/my_insert.py
maintain_ner_position/my_utils.py
maintain_ner_position-0.0.2.dist-info/LICENSE
maintain_ner_position-0.0.2.dist-info/METADATA
maintain_ner_position-0.0.2.dist-info/WHEEL
maintain_ner_position-0.0.2.dist-info/top_level.txt
maintain_ner_position-0.0.2.dist-info/RECORD
