Metadata-Version: 2.1
Name: maintain-ner-position
Version: 0.0.2
Summary: 本项目提供几个简单的对原始文本做增删改的函数，同时能够维护其实体列表中的各索引同步修改。
Home-page: https://github.com/wmc1992/maintain_ner_position
Author: wmc1992
Author-email: m18810541081@163.com
License: MIT
Keywords: NER 索引
Platform: UNKNOWN
Classifier: Programming Language :: Python :: 3
Classifier: License :: OSI Approved :: MIT License
Classifier: Operating System :: POSIX :: Linux
Requires-Python: >=3.6
License-File: LICENSE
